



  



  



  [
    {
        "key": "group_64008b7136380",
        "title": "Membership Content",
        "fields": [
            {
                "key": "field_6412a2ba5fd29",
                "label": "Title",
                "name": "title",
                "type": "text",
                "instructions": "",
                "required": 0,
                "conditional_logic": 0,
                "wrapper": {
                    "width": "",
                    "class": "",
                    "id": ""
                },
                "default_value": "",
                "placeholder": "",
                "prepend": "",
                "append": "",
                "maxlength": ""
            },
            {
                "key": "field_64008b8083fac",
                "label": "Benefits",
                "name": "content",
                "type": "repeater",
                "instructions": "",
                "required": 0,
                "conditional_logic": 0,
                "wrapper": {
                    "width": "",
                    "class": "",
                    "id": ""
                },
                "collapsed": "",
                "min": 0,
                "max": 0,
                "layout": "table",
                "button_label": "",
                "sub_fields": [
                    {
                        "key": "field_64008b8a83fad",
                        "label": "Contents",
                        "name": "contents",
                        "type": "text",
                        "instructions": "",
                        "required": 0,
                        "conditional_logic": 0,
                        "wrapper": {
                            "width": "",
                            "class": "",
                            "id": ""
                        },
                        "default_value": "",
                        "placeholder": "",
                        "prepend": "",
                        "append": "",
                        "maxlength": ""
                    }
                ]
            },
            {
                "key": "field_641069b8fd224",
                "label": "Price",
                "name": "price",
                "type": "text",
                "instructions": "",
                "required": 0,
                "conditional_logic": 0,
                "wrapper": {
                    "width": "",
                    "class": "",
                    "id": ""
                },
                "default_value": "",
                "placeholder": "",
                "prepend": "",
                "append": "",
                "maxlength": ""
            },
            {
                "key": "field_6412a2df6c491",
                "label": "Highlighted",
                "name": "highlighted",
                "type": "checkbox",
                "instructions": "",
                "required": 0,
                "conditional_logic": 0,
                "wrapper": {
                    "width": "",
                    "class": "",
                    "id": ""
                },
                "choices": {
                    "highlights": "highlights"
                },
                "allow_custom": 0,
                "default_value": [],
                "layout": "vertical",
                "toggle": 0,
                "return_format": "value",
                "save_custom": 0
            },
            {
                "key": "field_6412a2e83952d",
                "label": "Footer Text",
                "name": "footer_text",
                "type": "text",
                "instructions": "",
                "required": 0,
                "conditional_logic": 0,
                "wrapper": {
                    "width": "",
                    "class": "",
                    "id": ""
                },
                "default_value": "",
                "placeholder": "",
                "prepend": "",
                "append": "",
                "maxlength": ""
            },
            {
                "key": "field_6412a2ef28518",
                "label": "Button Text",
                "name": "button_text",
                "type": "text",
                "instructions": "",
                "required": 0,
                "conditional_logic": 0,
                "wrapper": {
                    "width": "",
                    "class": "",
                    "id": ""
                },
                "default_value": "",
                "placeholder": "",
                "prepend": "",
                "append": "",
                "maxlength": ""
            }
        ],
        "location": [
            [
                {
                    "param": "post_type",
                    "operator": "==",
                    "value": "memberpressproduct"
                }
            ]
        ],
        "menu_order": 0,
        "position": "normal",
        "style": "default",
        "label_placement": "top",
        "instruction_placement": "label",
        "hide_on_screen": "",
        "active": true,
        "description": "",
        "show_in_rest": 0
    },
    {
        "key": "group_63fc371e68773",
        "title": "User Custom Fields",
        "fields": [
            {
                "key": "field_63fc37333dd75",
                "label": "Wishlist Limit",
                "name": "wishlist_limit",
                "type": "number",
                "instructions": "",
                "required": 0,
                "conditional_logic": 0,
                "wrapper": {
                    "width": "",
                    "class": "",
                    "id": ""
                },
                "default_value": "",
                "placeholder": "",
                "prepend": "",
                "append": "",
                "min": "",
                "max": "",
                "step": ""
            }
        ],
        "location": [
            [
                {
                    "param": "user_form",
                    "operator": "==",
                    "value": "all"
                }
            ]
        ],
        "menu_order": 0,
        "position": "normal",
        "style": "default",
        "label_placement": "top",
        "instruction_placement": "label",
        "hide_on_screen": "",
        "active": true,
        "description": "",
        "show_in_rest": 0
    },
    {
        "key": "group_63f6e798bfd0b",
        "title": "API credentials",
        "fields": [
            {
                "key": "field_63f6eb99f472c",
                "label": "TransferMarket API",
                "name": "",
                "type": "tab",
                "instructions": "",
                "required": 0,
                "conditional_logic": 0,
                "wrapper": {
                    "width": "",
                    "class": "",
                    "id": ""
                },
                "placement": "top",
                "endpoint": 0
            },
            {
                "key": "field_63f6f080f472d",
                "label": "API Base URL",
                "name": "transfermarket_api_base_url_",
                "type": "url",
                "instructions": "",
                "required": 0,
                "conditional_logic": 0,
                "wrapper": {
                    "width": "",
                    "class": "",
                    "id": ""
                },
                "default_value": "",
                "placeholder": ""
            },
            {
                "key": "field_63f6e7ac024d9",
                "label": "API key",
                "name": "transfermarket_api",
                "type": "text",
                "instructions": "",
                "required": 0,
                "conditional_logic": 0,
                "wrapper": {
                    "width": "",
                    "class": "",
                    "id": ""
                },
                "default_value": "",
                "placeholder": "",
                "prepend": "",
                "append": "",
                "maxlength": ""
            },
            {
                "key": "field_63f6f0a4f472e",
                "label": "API Domain",
                "name": "transfermarket_api_domain_",
                "type": "text",
                "instructions": "",
                "required": 0,
                "conditional_logic": 0,
                "wrapper": {
                    "width": "",
                    "class": "",
                    "id": ""
                },
                "default_value": "",
                "placeholder": "",
                "prepend": "",
                "append": "",
                "maxlength": ""
            },
            {
                "key": "field_63f8834a803c9",
                "label": "soccer-football Api Cred",
                "name": "",
                "type": "tab",
                "instructions": "",
                "required": 0,
                "conditional_logic": 0,
                "wrapper": {
                    "width": "",
                    "class": "",
                    "id": ""
                },
                "placement": "top",
                "endpoint": 0
            },
            {
                "key": "field_63f88361803ca",
                "label": "soccer-football Api Base URL",
                "name": "soccer-football_api_base_url_",
                "type": "url",
                "instructions": "",
                "required": 0,
                "conditional_logic": 0,
                "wrapper": {
                    "width": "",
                    "class": "",
                    "id": ""
                },
                "default_value": "",
                "placeholder": ""
            },
            {
                "key": "field_63f88387803cc",
                "label": "soccer-football Api Base Host  Name",
                "name": "soccer-football_api_base_host__name",
                "type": "text",
                "instructions": "",
                "required": 0,
                "conditional_logic": 0,
                "wrapper": {
                    "width": "",
                    "class": "",
                    "id": ""
                },
                "default_value": "",
                "placeholder": "",
                "prepend": "",
                "append": "",
                "maxlength": ""
            },
            {
                "key": "field_63f88399803cd",
                "label": "soccer-football Api Base Api key",
                "name": "soccer-football_api_base_api_key",
                "type": "text",
                "instructions": "",
                "required": 0,
                "conditional_logic": 0,
                "wrapper": {
                    "width": "",
                    "class": "",
                    "id": ""
                },
                "default_value": "",
                "placeholder": "",
                "prepend": "",
                "append": "",
                "maxlength": ""
            },
            {
                "key": "field_63fc7c450609d",
                "label": "livescore-api Credi",
                "name": "",
                "type": "tab",
                "instructions": "",
                "required": 0,
                "conditional_logic": 0,
                "wrapper": {
                    "width": "",
                    "class": "",
                    "id": ""
                },
                "placement": "top",
                "endpoint": 0
            },
            {
                "key": "field_63fc7c540609e",
                "label": "livescore api Base URL",
                "name": "livescore_api_base_url_",
                "type": "url",
                "instructions": "",
                "required": 0,
                "conditional_logic": 0,
                "wrapper": {
                    "width": "",
                    "class": "",
                    "id": ""
                },
                "default_value": "",
                "placeholder": ""
            },
            {
                "key": "field_63fc7f2dfd271",
                "label": "livescore api Client ID",
                "name": "livescore_api_client_id",
                "type": "text",
                "instructions": "",
                "required": 0,
                "conditional_logic": 0,
                "wrapper": {
                    "width": "",
                    "class": "",
                    "id": ""
                },
                "default_value": "",
                "placeholder": "",
                "prepend": "",
                "append": "",
                "maxlength": ""
            },
            {
                "key": "field_63fc7c6f060a0",
                "label": "livescore api secret ID",
                "name": "livescore_api_secrate_id",
                "type": "text",
                "instructions": "",
                "required": 0,
                "conditional_logic": 0,
                "wrapper": {
                    "width": "",
                    "class": "",
                    "id": ""
                },
                "default_value": "",
                "placeholder": "",
                "prepend": "",
                "append": "",
                "maxlength": ""
            }
        ],
        "location": [
            [
                {
                    "param": "options_page",
                    "operator": "==",
                    "value": "theme-general-settings"
                }
            ]
        ],
        "menu_order": 0,
        "position": "normal",
        "style": "default",
        "label_placement": "top",
        "instruction_placement": "label",
        "hide_on_screen": "",
        "active": true,
        "description": "",
        "show_in_rest": 0
    },
    {
        "key": "group_63f5d3df27ed7",
        "title": "Secondary Homepage",
        "fields": [
            {
                "key": "field_63f5d3fb10b8e",
                "label": "Banner Image",
                "name": "banner_image",
                "type": "image",
                "instructions": "",
                "required": 0,
                "conditional_logic": 0,
                "wrapper": {
                    "width": "",
                    "class": "",
                    "id": ""
                },
                "return_format": "url",
                "preview_size": "medium",
                "library": "all",
                "min_width": "",
                "min_height": "",
                "min_size": "",
                "max_width": "",
                "max_height": "",
                "max_size": "",
                "mime_types": ""
            },
            {
                "key": "field_63f5d40e10b8f",
                "label": "Search Thousands of Player stats",
                "name": "search_thousands_of_player_stats",
                "type": "text",
                "instructions": "",
                "required": 0,
                "conditional_logic": 0,
                "wrapper": {
                    "width": "",
                    "class": "",
                    "id": ""
                },
                "default_value": "Search Thousands of Player stats",
                "placeholder": "",
                "prepend": "",
                "append": "",
                "maxlength": ""
            },
            {
                "key": "field_63f5d41710b90",
                "label": "View All Butoon Link",
                "name": "view_all_butoon_link",
                "type": "text",
                "instructions": "",
                "required": 0,
                "conditional_logic": 0,
                "wrapper": {
                    "width": "",
                    "class": "",
                    "id": ""
                },
                "default_value": "",
                "placeholder": "",
                "prepend": "",
                "append": "",
                "maxlength": ""
            },
            {
                "key": "field_63f5d42210b91",
                "label": "View All Button",
                "name": "view_all_button",
                "type": "text",
                "instructions": "",
                "required": 0,
                "conditional_logic": 0,
                "wrapper": {
                    "width": "",
                    "class": "",
                    "id": ""
                },
                "default_value": "",
                "placeholder": "",
                "prepend": "",
                "append": "",
                "maxlength": ""
            },
            {
                "key": "field_63f5d43f10b92",
                "label": "Search Player By Name",
                "name": "search_player_by_name",
                "type": "text",
                "instructions": "",
                "required": 0,
                "conditional_logic": 0,
                "wrapper": {
                    "width": "",
                    "class": "",
                    "id": ""
                },
                "default_value": "Search Player By Name",
                "placeholder": "",
                "prepend": "",
                "append": "",
                "maxlength": ""
            },
            {
                "key": "field_63f5d45610b94",
                "label": "Search Player By Name Image",
                "name": "search_player_by_name_image",
                "type": "image",
                "instructions": "",
                "required": 0,
                "conditional_logic": 0,
                "wrapper": {
                    "width": "",
                    "class": "",
                    "id": ""
                },
                "return_format": "url",
                "preview_size": "medium",
                "library": "all",
                "min_width": "",
                "min_height": "",
                "min_size": "",
                "max_width": "",
                "max_height": "",
                "max_size": "",
                "mime_types": ""
            },
            {
                "key": "field_63f5d44c10b93",
                "label": "Search Player By Country",
                "name": "search_player_by_country",
                "type": "text",
                "instructions": "",
                "required": 0,
                "conditional_logic": 0,
                "wrapper": {
                    "width": "",
                    "class": "",
                    "id": ""
                },
                "default_value": "",
                "placeholder": "",
                "prepend": "",
                "append": "",
                "maxlength": ""
            },
            {
                "key": "field_63f5d46710b95",
                "label": "Search Player By Country Image",
                "name": "search_player_by_country_image",
                "type": "image",
                "instructions": "",
                "required": 0,
                "conditional_logic": 0,
                "wrapper": {
                    "width": "",
                    "class": "",
                    "id": ""
                },
                "return_format": "url",
                "preview_size": "medium",
                "library": "all",
                "min_width": "",
                "min_height": "",
                "min_size": "",
                "max_width": "",
                "max_height": "",
                "max_size": "",
                "mime_types": ""
            }
        ],
        "location": [
            [
                {
                    "param": "page_template",
                    "operator": "==",
                    "value": "Secondary-homepage.php"
                }
            ]
        ],
        "menu_order": 0,
        "position": "normal",
        "style": "default",
        "label_placement": "top",
        "instruction_placement": "label",
        "hide_on_screen": "",
        "active": true,
        "description": "",
        "show_in_rest": 0
    },
    {
        "key": "group_63ef557b0b012",
        "title": "Plan and pricing",
        "fields": [
            {
                "key": "field_63ef5596461dd",
                "label": "Banner",
                "name": "banner",
                "type": "image",
                "instructions": "",
                "required": 0,
                "conditional_logic": 0,
                "wrapper": {
                    "width": "",
                    "class": "",
                    "id": ""
                },
                "return_format": "url",
                "preview_size": "medium",
                "library": "all",
                "min_width": "",
                "min_height": "",
                "min_size": "",
                "max_width": "",
                "max_height": "",
                "max_size": "",
                "mime_types": ""
            }
        ],
        "location": [
            [
                {
                    "param": "page_template",
                    "operator": "==",
                    "value": "Pricing.php"
                }
            ]
        ],
        "menu_order": 0,
        "position": "normal",
        "style": "default",
        "label_placement": "top",
        "instruction_placement": "label",
        "hide_on_screen": "",
        "active": true,
        "description": "",
        "show_in_rest": 0
    },
    {
        "key": "group_63ee18276816a",
        "title": "faq Section",
        "fields": [
            {
                "key": "field_63ee18b7aff71",
                "label": "faq Section  Tab",
                "name": "",
                "type": "tab",
                "instructions": "",
                "required": 0,
                "conditional_logic": 0,
                "wrapper": {
                    "width": "",
                    "class": "",
                    "id": ""
                },
                "placement": "top",
                "endpoint": 0
            },
            {
                "key": "field_63ee18caaff72",
                "label": "faq Section Title",
                "name": "faq_section_title_",
                "type": "text",
                "instructions": "",
                "required": 0,
                "conditional_logic": 0,
                "wrapper": {
                    "width": "",
                    "class": "",
                    "id": ""
                },
                "default_value": "",
                "placeholder": "",
                "prepend": "",
                "append": "",
                "maxlength": ""
            },
            {
                "key": "field_63ee18e0aff74",
                "label": "faq Queries",
                "name": "faq_queries",
                "type": "repeater",
                "instructions": "",
                "required": 0,
                "conditional_logic": 0,
                "wrapper": {
                    "width": "",
                    "class": "",
                    "id": ""
                },
                "collapsed": "",
                "min": 0,
                "max": 0,
                "layout": "table",
                "button_label": "",
                "sub_fields": [
                    {
                        "key": "field_63ee18fbaff76",
                        "label": "faq Queries Question",
                        "name": "faq_queries_question",
                        "type": "text",
                        "instructions": "",
                        "required": 0,
                        "conditional_logic": 0,
                        "wrapper": {
                            "width": "",
                            "class": "",
                            "id": ""
                        },
                        "default_value": "",
                        "placeholder": "",
                        "prepend": "",
                        "append": "",
                        "maxlength": ""
                    },
                    {
                        "key": "field_63ee191caff77",
                        "label": "faq Queries Answer",
                        "name": "faq_queries_answer",
                        "type": "textarea",
                        "instructions": "",
                        "required": 0,
                        "conditional_logic": 0,
                        "wrapper": {
                            "width": "",
                            "class": "",
                            "id": ""
                        },
                        "default_value": "",
                        "placeholder": "",
                        "maxlength": "",
                        "rows": "",
                        "new_lines": ""
                    }
                ]
            }
        ],
        "location": [
            [
                {
                    "param": "page_template",
                    "operator": "==",
                    "value": "faq.php"
                }
            ]
        ],
        "menu_order": 0,
        "position": "normal",
        "style": "default",
        "label_placement": "top",
        "instruction_placement": "label",
        "hide_on_screen": "",
        "active": true,
        "description": "",
        "show_in_rest": 0
    },
    {
        "key": "group_63ee0c21311c1",
        "title": "Contact Us Section",
        "fields": [
            {
                "key": "field_63ee0c34ccaef",
                "label": "Contact Us Section",
                "name": "",
                "type": "tab",
                "instructions": "",
                "required": 0,
                "conditional_logic": 0,
                "wrapper": {
                    "width": "",
                    "class": "",
                    "id": ""
                },
                "placement": "top",
                "endpoint": 0
            },
            {
                "key": "field_63ee0c45ccaf0",
                "label": "Contact Us Section Title",
                "name": "contact_us_section_title",
                "type": "text",
                "instructions": "",
                "required": 0,
                "conditional_logic": 0,
                "wrapper": {
                    "width": "",
                    "class": "",
                    "id": ""
                },
                "default_value": "",
                "placeholder": "",
                "prepend": "",
                "append": "",
                "maxlength": ""
            },
            {
                "key": "field_63ee0c68ccaf1",
                "label": "Contact Us Section Subtitle",
                "name": "contact_us_section_subtitle",
                "type": "text",
                "instructions": "",
                "required": 0,
                "conditional_logic": 0,
                "wrapper": {
                    "width": "",
                    "class": "",
                    "id": ""
                },
                "default_value": "",
                "placeholder": "",
                "prepend": "",
                "append": "",
                "maxlength": ""
            },
            {
                "key": "field_63ee0cbfccaf2",
                "label": "Contact Us Section Ads Section",
                "name": "contact_us_section_ads_section",
                "type": "gallery",
                "instructions": "",
                "required": 0,
                "conditional_logic": 0,
                "wrapper": {
                    "width": "",
                    "class": "",
                    "id": ""
                },
                "return_format": "array",
                "preview_size": "medium",
                "insert": "append",
                "library": "all",
                "min": "",
                "max": "",
                "min_width": "",
                "min_height": "",
                "min_size": "",
                "max_width": "",
                "max_height": "",
                "max_size": "",
                "mime_types": ""
            }
        ],
        "location": [
            [
                {
                    "param": "page_template",
                    "operator": "==",
                    "value": "Contact-us.php"
                }
            ]
        ],
        "menu_order": 0,
        "position": "normal",
        "style": "default",
        "label_placement": "top",
        "instruction_placement": "label",
        "hide_on_screen": "",
        "active": true,
        "description": "",
        "show_in_rest": 0
    },
    {
        "key": "group_63edfcce93888",
        "title": "About Us Page",
        "fields": [
            {
                "key": "field_63edfcf48a921",
                "label": "About Us Banner Section",
                "name": "",
                "type": "tab",
                "instructions": "",
                "required": 0,
                "conditional_logic": 0,
                "wrapper": {
                    "width": "",
                    "class": "",
                    "id": ""
                },
                "placement": "top",
                "endpoint": 0
            },
            {
                "key": "field_63edfd058a922",
                "label": "About Us Banner Section Text",
                "name": "about_us_banner_section_text",
                "type": "text",
                "instructions": "",
                "required": 0,
                "conditional_logic": 0,
                "wrapper": {
                    "width": "",
                    "class": "",
                    "id": ""
                },
                "default_value": "",
                "placeholder": "",
                "prepend": "",
                "append": "",
                "maxlength": ""
            },
            {
                "key": "field_63edfd3a8a923",
                "label": "About Us Banner Section Background Image",
                "name": "about_us_banner_section_background_image",
                "type": "file",
                "instructions": "",
                "required": 0,
                "conditional_logic": 0,
                "wrapper": {
                    "width": "",
                    "class": "",
                    "id": ""
                },
                "return_format": "url",
                "library": "all",
                "min_size": "",
                "max_size": "",
                "mime_types": ""
            },
            {
                "key": "field_63edfd713584d",
                "label": "About us Section Tab",
                "name": "",
                "type": "tab",
                "instructions": "",
                "required": 0,
                "conditional_logic": 0,
                "wrapper": {
                    "width": "",
                    "class": "",
                    "id": ""
                },
                "placement": "top",
                "endpoint": 0
            },
            {
                "key": "field_63edfdb33584f",
                "label": "About us Section text",
                "name": "about_us_section_text",
                "type": "text",
                "instructions": "",
                "required": 0,
                "conditional_logic": 0,
                "wrapper": {
                    "width": "",
                    "class": "",
                    "id": ""
                },
                "default_value": "",
                "placeholder": "",
                "prepend": "",
                "append": "",
                "maxlength": ""
            },
            {
                "key": "field_63edfdd135850",
                "label": "About us Section Heading text",
                "name": "about_us_section_heading_text",
                "type": "text",
                "instructions": "",
                "required": 0,
                "conditional_logic": 0,
                "wrapper": {
                    "width": "",
                    "class": "",
                    "id": ""
                },
                "default_value": "",
                "placeholder": "",
                "prepend": "",
                "append": "",
                "maxlength": ""
            },
            {
                "key": "field_63edfdf335851",
                "label": "About us Section Description",
                "name": "about_us_section_description",
                "type": "textarea",
                "instructions": "",
                "required": 0,
                "conditional_logic": 0,
                "wrapper": {
                    "width": "",
                    "class": "",
                    "id": ""
                },
                "default_value": "",
                "placeholder": "",
                "maxlength": "",
                "rows": "",
                "new_lines": ""
            },
            {
                "key": "field_63edfe1435852",
                "label": "About us Section Image",
                "name": "about_us_section_image",
                "type": "file",
                "instructions": "",
                "required": 0,
                "conditional_logic": 0,
                "wrapper": {
                    "width": "",
                    "class": "",
                    "id": ""
                },
                "return_format": "url",
                "library": "all",
                "min_size": "",
                "max_size": "",
                "mime_types": ""
            },
            {
                "key": "field_63edfe7735853",
                "label": "league Table Section",
                "name": "",
                "type": "tab",
                "instructions": "",
                "required": 0,
                "conditional_logic": 0,
                "wrapper": {
                    "width": "",
                    "class": "",
                    "id": ""
                },
                "placement": "top",
                "endpoint": 0
            },
            {
                "key": "field_63edff1435859",
                "label": "league Table Section Background Image",
                "name": "league_table_section_background_image",
                "type": "file",
                "instructions": "",
                "required": 0,
                "conditional_logic": 0,
                "wrapper": {
                    "width": "",
                    "class": "",
                    "id": ""
                },
                "return_format": "url",
                "library": "all",
                "min_size": "",
                "max_size": "",
                "mime_types": ""
            },
            {
                "key": "field_63edfef535858",
                "label": "league Table Section Images",
                "name": "league_table_section_images",
                "type": "file",
                "instructions": "",
                "required": 0,
                "conditional_logic": 0,
                "wrapper": {
                    "width": "",
                    "class": "",
                    "id": ""
                },
                "return_format": "url",
                "library": "all",
                "min_size": "",
                "max_size": "",
                "mime_types": ""
            },
            {
                "key": "field_63edfea435855",
                "label": "league Table Section Title",
                "name": "league_table_section_title",
                "type": "text",
                "instructions": "",
                "required": 0,
                "conditional_logic": 0,
                "wrapper": {
                    "width": "",
                    "class": "",
                    "id": ""
                },
                "default_value": "",
                "placeholder": "",
                "prepend": "",
                "append": "",
                "maxlength": ""
            },
            {
                "key": "field_63edfec435856",
                "label": "league Table Section Sub title",
                "name": "league_table_section_sub_title",
                "type": "text",
                "instructions": "",
                "required": 0,
                "conditional_logic": 0,
                "wrapper": {
                    "width": "",
                    "class": "",
                    "id": ""
                },
                "default_value": "",
                "placeholder": "",
                "prepend": "",
                "append": "",
                "maxlength": ""
            },
            {
                "key": "field_63edfedb35857",
                "label": "league Table Section Description",
                "name": "league_table_section_description",
                "type": "textarea",
                "instructions": "",
                "required": 0,
                "conditional_logic": 0,
                "wrapper": {
                    "width": "",
                    "class": "",
                    "id": ""
                },
                "default_value": "",
                "placeholder": "",
                "maxlength": "",
                "rows": "",
                "new_lines": ""
            },
            {
                "key": "field_63edff5e3585b",
                "label": "Testimonials Section",
                "name": "",
                "type": "tab",
                "instructions": "",
                "required": 0,
                "conditional_logic": 0,
                "wrapper": {
                    "width": "",
                    "class": "",
                    "id": ""
                },
                "placement": "top",
                "endpoint": 0
            },
            {
                "key": "field_63edff783585d",
                "label": "Testimonials Section Title",
                "name": "testimonials_section_title",
                "type": "text",
                "instructions": "",
                "required": 0,
                "conditional_logic": 0,
                "wrapper": {
                    "width": "",
                    "class": "",
                    "id": ""
                },
                "default_value": "",
                "placeholder": "",
                "prepend": "",
                "append": "",
                "maxlength": ""
            },
            {
                "key": "field_63edffa43585f",
                "label": "Testimonials Section Sub title",
                "name": "testimonials_section_sub_title_",
                "type": "text",
                "instructions": "",
                "required": 0,
                "conditional_logic": 0,
                "wrapper": {
                    "width": "",
                    "class": "",
                    "id": ""
                },
                "default_value": "",
                "placeholder": "",
                "prepend": "",
                "append": "",
                "maxlength": ""
            },
            {
                "key": "field_63ee09b3343ec",
                "label": "Ads Banner Section",
                "name": "",
                "type": "tab",
                "instructions": "",
                "required": 0,
                "conditional_logic": 0,
                "wrapper": {
                    "width": "",
                    "class": "",
                    "id": ""
                },
                "placement": "top",
                "endpoint": 0
            },
            {
                "key": "field_63ee0a1d343f0",
                "label": "Ads Banner Section part 1 background image",
                "name": "ads_banner_section_part_1_background_image_",
                "type": "file",
                "instructions": "",
                "required": 0,
                "conditional_logic": 0,
                "wrapper": {
                    "width": "",
                    "class": "",
                    "id": ""
                },
                "return_format": "url",
                "library": "all",
                "min_size": "",
                "max_size": "",
                "mime_types": ""
            },
            {
                "key": "field_63ee0a4d343f1",
                "label": "Ads Banner Section part 2 background image",
                "name": "ads_banner_section_part_2_background_image",
                "type": "file",
                "instructions": "",
                "required": 0,
                "conditional_logic": 0,
                "wrapper": {
                    "width": "",
                    "class": "",
                    "id": ""
                },
                "return_format": "url",
                "library": "all",
                "min_size": "",
                "max_size": "",
                "mime_types": ""
            },
            {
                "key": "field_63ee0a8e343f2",
                "label": "Ads Banner Section close image",
                "name": "ads_banner_section_close_image",
                "type": "file",
                "instructions": "",
                "required": 0,
                "conditional_logic": 0,
                "wrapper": {
                    "width": "",
                    "class": "",
                    "id": ""
                },
                "return_format": "url",
                "library": "all",
                "min_size": "",
                "max_size": "",
                "mime_types": ""
            }
        ],
        "location": [
            [
                {
                    "param": "page_template",
                    "operator": "==",
                    "value": "About.php"
                }
            ]
        ],
        "menu_order": 0,
        "position": "normal",
        "style": "default",
        "label_placement": "top",
        "instruction_placement": "label",
        "hide_on_screen": "",
        "active": true,
        "description": "",
        "show_in_rest": 0
    },
    {
        "key": "group_63edbd1626028",
        "title": "Player Stats",
        "fields": [
            {
                "key": "field_63edbda40a0fb",
                "label": "Player ID",
                "name": "player_id",
                "type": "text",
                "instructions": "",
                "required": 0,
                "conditional_logic": 0,
                "wrapper": {
                    "width": "",
                    "class": "",
                    "id": ""
                },
                "default_value": "",
                "placeholder": "",
                "prepend": "",
                "append": "",
                "maxlength": ""
            }
        ],
        "location": [
            [
                {
                    "param": "options_page",
                    "operator": "==",
                    "value": "acf-options-player-stats"
                }
            ]
        ],
        "menu_order": 0,
        "position": "normal",
        "style": "default",
        "label_placement": "top",
        "instruction_placement": "label",
        "hide_on_screen": "",
        "active": true,
        "description": "",
        "show_in_rest": 0
    },
    {
        "key": "group_63eb7d21bffaf",
        "title": "Footer Section",
        "fields": [
            {
                "key": "field_63eb7d2877585",
                "label": "Copyright",
                "name": "copyright",
                "type": "text",
                "instructions": "",
                "required": 0,
                "conditional_logic": 0,
                "wrapper": {
                    "width": "",
                    "class": "",
                    "id": ""
                },
                "default_value": "",
                "placeholder": "",
                "prepend": "",
                "append": "",
                "maxlength": ""
            },
            {
                "key": "field_63ecca84a9efd",
                "label": "Footer Logo",
                "name": "footer_logo",
                "type": "image",
                "instructions": "",
                "required": 0,
                "conditional_logic": 0,
                "wrapper": {
                    "width": "",
                    "class": "",
                    "id": ""
                },
                "return_format": "url",
                "preview_size": "medium",
                "library": "all",
                "min_width": "",
                "min_height": "",
                "min_size": "",
                "max_width": "",
                "max_height": "",
                "max_size": "",
                "mime_types": ""
            },
            {
                "key": "field_63eccaaea9efe",
                "label": "footer Logo Link",
                "name": "footer_logo_link",
                "type": "text",
                "instructions": "",
                "required": 0,
                "conditional_logic": 0,
                "wrapper": {
                    "width": "",
                    "class": "",
                    "id": ""
                },
                "default_value": "",
                "placeholder": "",
                "prepend": "",
                "append": "",
                "maxlength": ""
            }
        ],
        "location": [
            [
                {
                    "param": "options_page",
                    "operator": "==",
                    "value": "acf-options-footer"
                }
            ]
        ],
        "menu_order": 0,
        "position": "normal",
        "style": "default",
        "label_placement": "top",
        "instruction_placement": "label",
        "hide_on_screen": "",
        "active": true,
        "description": "",
        "show_in_rest": 0
    },
    {
        "key": "group_63eb7cc959656",
        "title": "Header Section",
        "fields": [
            {
                "key": "field_63eb7cd5d494a",
                "label": "Logo",
                "name": "logo",
                "type": "image",
                "instructions": "",
                "required": 0,
                "conditional_logic": 0,
                "wrapper": {
                    "width": "",
                    "class": "",
                    "id": ""
                },
                "return_format": "url",
                "preview_size": "medium",
                "library": "all",
                "min_width": "",
                "min_height": "",
                "min_size": "",
                "max_width": "",
                "max_height": "",
                "max_size": "",
                "mime_types": ""
            },
            {
                "key": "field_63eb7ce3d494b",
                "label": "Social Icons",
                "name": "social_icons",
                "type": "repeater",
                "instructions": "",
                "required": 0,
                "conditional_logic": 0,
                "wrapper": {
                    "width": "",
                    "class": "",
                    "id": ""
                },
                "collapsed": "",
                "min": 0,
                "max": 0,
                "layout": "table",
                "button_label": "",
                "sub_fields": [
                    {
                        "key": "field_63eb7cf2d494c",
                        "label": "Image",
                        "name": "image",
                        "type": "image",
                        "instructions": "",
                        "required": 0,
                        "conditional_logic": 0,
                        "wrapper": {
                            "width": "",
                            "class": "",
                            "id": ""
                        },
                        "return_format": "url",
                        "preview_size": "medium",
                        "library": "all",
                        "min_width": "",
                        "min_height": "",
                        "min_size": "",
                        "max_width": "",
                        "max_height": "",
                        "max_size": "",
                        "mime_types": ""
                    },
                    {
                        "key": "field_63eb7d07d494d",
                        "label": "Link",
                        "name": "link",
                        "type": "text",
                        "instructions": "",
                        "required": 0,
                        "conditional_logic": 0,
                        "wrapper": {
                            "width": "",
                            "class": "",
                            "id": ""
                        },
                        "default_value": "",
                        "placeholder": "",
                        "prepend": "",
                        "append": "",
                        "maxlength": ""
                    }
                ]
            }
        ],
        "location": [
            [
                {
                    "param": "options_page",
                    "operator": "==",
                    "value": "acf-options-header"
                }
            ]
        ],
        "menu_order": 0,
        "position": "normal",
        "style": "default",
        "label_placement": "top",
        "instruction_placement": "label",
        "hide_on_screen": "",
        "active": true,
        "description": "",
        "show_in_rest": 0
    },
    {
        "key": "group_63eb4dcd69a97",
        "title": "Home",
        "fields": [
            {
                "key": "field_63eb4de443006",
                "label": "Banner",
                "name": "banner",
                "type": "repeater",
                "instructions": "",
                "required": 0,
                "conditional_logic": 0,
                "wrapper": {
                    "width": "",
                    "class": "",
                    "id": ""
                },
                "collapsed": "",
                "min": 0,
                "max": 0,
                "layout": "table",
                "button_label": "",
                "sub_fields": [
                    {
                        "key": "field_63eb4eab6e228",
                        "label": "Banner Image",
                        "name": "banner_image",
                        "type": "image",
                        "instructions": "",
                        "required": 0,
                        "conditional_logic": 0,
                        "wrapper": {
                            "width": "",
                            "class": "",
                            "id": ""
                        },
                        "return_format": "array",
                        "preview_size": "medium",
                        "library": "all",
                        "min_width": "",
                        "min_height": "",
                        "min_size": "",
                        "max_width": "",
                        "max_height": "",
                        "max_size": "",
                        "mime_types": ""
                    },
                    {
                        "key": "field_63eb4e14d8d9d",
                        "label": "Banner Logo",
                        "name": "banner_logo",
                        "type": "image",
                        "instructions": "",
                        "required": 0,
                        "conditional_logic": 0,
                        "wrapper": {
                            "width": "",
                            "class": "",
                            "id": ""
                        },
                        "return_format": "array",
                        "preview_size": "medium",
                        "library": "all",
                        "min_width": "",
                        "min_height": "",
                        "min_size": "",
                        "max_width": "",
                        "max_height": "",
                        "max_size": "",
                        "mime_types": ""
                    },
                    {
                        "key": "field_63eb4e1ed8d9e",
                        "label": "Banner Title",
                        "name": "banner_title",
                        "type": "text",
                        "instructions": "",
                        "required": 0,
                        "conditional_logic": 0,
                        "wrapper": {
                            "width": "",
                            "class": "",
                            "id": ""
                        },
                        "default_value": "",
                        "placeholder": "",
                        "prepend": "",
                        "append": "",
                        "maxlength": ""
                    }
                ]
            },
            {
                "key": "field_63eefdad660df",
                "label": "Search Image",
                "name": "search_image",
                "type": "file",
                "instructions": "",
                "required": 0,
                "conditional_logic": 0,
                "wrapper": {
                    "width": "",
                    "class": "",
                    "id": ""
                },
                "return_format": "url",
                "library": "all",
                "min_size": "",
                "max_size": "",
                "mime_types": ""
            },
            {
                "key": "field_63eefe07660e0",
                "label": "Player Stats Text",
                "name": "player_stats_text_",
                "type": "text",
                "instructions": "",
                "required": 0,
                "conditional_logic": 0,
                "wrapper": {
                    "width": "",
                    "class": "",
                    "id": ""
                },
                "default_value": "",
                "placeholder": "",
                "prepend": "",
                "append": "",
                "maxlength": ""
            },
            {
                "key": "field_63eefe18660e1",
                "label": "View Played Text",
                "name": "view_played_text",
                "type": "text",
                "instructions": "",
                "required": 0,
                "conditional_logic": 0,
                "wrapper": {
                    "width": "",
                    "class": "",
                    "id": ""
                },
                "default_value": "",
                "placeholder": "",
                "prepend": "",
                "append": "",
                "maxlength": ""
            },
            {
                "key": "field_63eefe1b660e2",
                "label": "Live Score Text",
                "name": "live_score_text",
                "type": "text",
                "instructions": "",
                "required": 0,
                "conditional_logic": 0,
                "wrapper": {
                    "width": "",
                    "class": "",
                    "id": ""
                },
                "default_value": "",
                "placeholder": "",
                "prepend": "",
                "append": "",
                "maxlength": ""
            },
            {
                "key": "field_63eefe49660e3",
                "label": "News Section Text",
                "name": "news_section_text",
                "type": "text",
                "instructions": "",
                "required": 0,
                "conditional_logic": 0,
                "wrapper": {
                    "width": "",
                    "class": "",
                    "id": ""
                },
                "default_value": "",
                "placeholder": "",
                "prepend": "",
                "append": "",
                "maxlength": ""
            },
            {
                "key": "field_63eefe54660e4",
                "label": "News Section Image",
                "name": "news_section_image",
                "type": "file",
                "instructions": "",
                "required": 0,
                "conditional_logic": 0,
                "wrapper": {
                    "width": "",
                    "class": "",
                    "id": ""
                },
                "return_format": "url",
                "library": "all",
                "min_size": "",
                "max_size": "",
                "mime_types": ""
            }
        ],
        "location": [
            [
                {
                    "param": "page_template",
                    "operator": "==",
                    "value": "Homepage.php"
                }
            ]
        ],
        "menu_order": 0,
        "position": "normal",
        "style": "default",
        "label_placement": "top",
        "instruction_placement": "label",
        "hide_on_screen": "",
        "active": true,
        "description": "",
        "show_in_rest": 0
    }
]